pyRothC/RothC.py
pyRothC/__init__.py
pyrothc-0.0.4.dist-info/METADATA
pyrothc-0.0.4.dist-info/WHEEL
pyrothc-0.0.4.dist-info/licenses/LICENSE
pyrothc-0.0.4.dist-info/RECORD
