Metadata-Version: 2.1
Name: pyRothC
Version: 0.0.4
Summary: Python version of The Rothamsted carbon model (RothC) 26.3. RothC is a model for the turnover of organic carbon in non-waterlogged topsoil that allows for the effects of soil type, temperature, soil moisture and plant cover on the turnover process.
Project-URL: Documentation, https://mishagrol.github.io
Project-URL: Source code, https://github.com/mishagrol/pyRothC
Author-email: Misha Grol <grol81@mail.ru>
Maintainer: misha grol
License: Creative Commons Legal Code
License-File: LICENSE
Classifier: Development Status :: 3 - Alpha
Classifier: Intended Audience :: Developers
Classifier: Intended Audience :: End Users/Desktop
Classifier: Intended Audience :: Science/Research
Classifier: License :: CC0 1.0 Universal (CC0 1.0) Public Domain Dedication
Classifier: Operating System :: OS Independent
Classifier: Programming Language :: Python :: 3
Classifier: Programming Language :: Python :: 3.7
Classifier: Programming Language :: Python :: 3.8
Classifier: Programming Language :: Python :: 3.9
Requires-Python: >=3.7
Requires-Dist: numpy>=1.20.3
Requires-Dist: pandas>=1.3.4
Requires-Dist: scipy>=1.7.3
Provides-Extra: test
Requires-Dist: pytest; extra == 'test'
